{"name":"Destiny","author":"lettergrade","created":"2018-03-09","skill":"Restart","main":[{"name":"Black Luster Soldier - Sacred Soldier","amount":1},{"name":"Black Luster Soldier - Sacred Soldier","amount":1},{"name":"Black Luster Soldier - Sacred Soldier","amount":1},{"name":"Destiny HERO - Celestial","amount":1},{"name":"Destiny HERO - Celestial","amount":1},{"name":"Destiny HERO - Celestial","amount":1},{"name":"Destiny HERO - Decider","amount":1},{"name":"The Dark - Hex-Sealed Fusion","amount":1},{"name":"The Dark - Hex-Sealed Fusion","amount":1},{"name":"The Dark - Hex-Sealed Fusion","amount":1},{"name":"Vision HERO Vyon","amount":1},{"name":"Vision HERO Vyon","amount":1},{"name":"Vision HERO Vyon","amount":1},{"name":"Destiny HERO - Malicious","amount":1},{"name":"Destiny HERO - Malicious","amount":1},{"name":"Destiny HERO - Dreamer","amount":1},{"name":"Destiny HERO - Dreamer","amount":1},{"name":"Destiny Draw","amount":1},{"name":"Polymerization","amount":1},{"name":"Polymerization","amount":1},{"name":"Polymerization","amount":1},{"name":"Beginning of Heaven and Earth","amount":1},{"name":"Beginning of Heaven and Earth","amount":1},{"name":"Beginning of Heaven and Earth","amount":1},{"name":"Powerful Rebirth","amount":1},{"name":"Powerful Rebirth","amount":1},{"name":"Powerful Rebirth","amount":1}],"extra":[],"notes":[{"text":"Not optimized but at least the decklist is easy on my OCD"}],"url":"/top-decks/march-2018/destiny-heroes/destiny-by-lettergrade/"}
