{"name":"##","top-player-council":false,"author":"coalvarez21","created":"2018-05-08","skill":"Restart","main":[{"name":"Amazoness Queen","amount":1},{"name":"Amazoness Swords Woman","amount":1},{"name":"Amazoness Swords Woman","amount":1},{"name":"Amazoness Swords Woman","amount":1},{"name":"Amazoness Sage","amount":1},{"name":"Amazoness Princess","amount":1},{"name":"Amazoness Princess","amount":1},{"name":"Amazoness Princess","amount":1},{"name":"Amazoness Tiger","amount":1},{"name":"Amazoness Baby Tiger","amount":1},{"name":"Amazoness Scouts","amount":1},{"name":"Enemy Controller","amount":1},{"name":"Enemy Controller","amount":1},{"name":"Forbidden Chalice","amount":1},{"name":"Super Rush Headlong","amount":1},{"name":"Super Rush Headlong","amount":1},{"name":"Amazoness Onslaught","amount":1},{"name":"Amazoness Onslaught","amount":1},{"name":"Amazoness Onslaught","amount":1},{"name":"Memory Loss","amount":1}],"extra":[],"notes":[{"text":"Scouts helped me against sylvans, memory loss also helped with sylvans and cyber angels. Didnt really like rebirth and willpower cuz i wanted more protection and more monsters to spam in the mirror match. Tiger offered pseudo protection. Fastest kog yet"}],"url":"/top-decks/may-2018/amazoness/-by-coalvarez21/"}
