{"name":"Destiny","top-player-council":false,"author":"Vyzual","created":"2018-04-06","skill":"Destiny Calling","main":[{"name":"Destiny HERO - Celestial","amount":1},{"name":"Destiny HERO - Celestial","amount":1},{"name":"Destiny HERO - Celestial","amount":1},{"name":"Destiny HERO - Decider","amount":1},{"name":"Destiny HERO - Decider","amount":1},{"name":"Destiny HERO - Decider","amount":1},{"name":"Destiny HERO - Drilldark","amount":1},{"name":"Destiny HERO - Drilldark","amount":1},{"name":"Destiny HERO - Drilldark","amount":1},{"name":"Cosmic Cyclone","amount":1},{"name":"Cosmic Cyclone","amount":1},{"name":"Enemy Controller","amount":1},{"name":"Enemy Controller","amount":1},{"name":"Forbidden Chalice","amount":1},{"name":"Forbidden Chalice","amount":1},{"name":"Mask Change","amount":1},{"name":"Mask Change","amount":1},{"name":"Mask Change","amount":1},{"name":"Wall of Disruption","amount":1},{"name":"Wall of Disruption","amount":1}],"extra":[{"name":"Masked HERO Anki","amount":1},{"name":"Masked HERO Anki","amount":1},{"name":"Masked HERO Anki","amount":1}],"notes":[{"text":"Only lost 1 out of 15 Games to Sylvians.\r\nAll other matchups were against SSA/ Fishes/ Archfiends\r\nLost 4 games in Total from Plat 3 to KoG and 3 of the loses were  OTKs by an Archfiend/ Darkworld  Deck"}],"url":"/top-decks/april-2018/masked-heroes/destiny-by-vyzual/"}
