{"name":"Aliens","top-player-council":false,"author":"nacseo","created":"2018-05-24","skill":"Restart","main":[{"name":"Alien Overlord","amount":1},{"name":"Alien Overlord","amount":1},{"name":"Alien Warrior","amount":1},{"name":"Alien Warrior","amount":1},{"name":"Alien Warrior","amount":1},{"name":"Alien Kid","amount":1},{"name":"Alien Telepath","amount":1},{"name":"Alien Telepath","amount":1},{"name":"\"A\" Cell Recombination Device","amount":1},{"name":"\"A\" Cell Recombination Device","amount":1},{"name":"\"A\" Cell Recombination Device","amount":1},{"name":"Cosmic Cyclone","amount":1},{"name":"Enemy Controller","amount":1},{"name":"Enemy Controller","amount":1},{"name":"Forbidden Chalice","amount":1},{"name":"Forbidden Chalice","amount":1},{"name":"Offerings to the Doomed","amount":1},{"name":"Offerings to the Doomed","amount":1},{"name":"Powerful Rebirth","amount":1},{"name":"Powerful Rebirth","amount":1}],"extra":[],"notes":[{"text":"offerings works very well with aliens... cc for more consistent backrow removal... after all easier kog than i expected"}],"url":"/top-decks/may-2018/aliens/aliens-by-nacseo/"}
