{"name":"Emperor of Bacon","top-player-council":false,"author":"Bacon - Fiend Expert","created":"2018-04-04","skill":"Restart","main":[{"name":"Archfiend Emperor, the First Lord of Horror","amount":1},{"name":"Archfiend Emperor, the First Lord of Horror","amount":1},{"name":"Archfiend Emperor, the First Lord of Horror","amount":1},{"name":"Archfiend Empress","amount":1},{"name":"Archfiend Empress","amount":1},{"name":"Archfiend Empress","amount":1},{"name":"Archfiend Cavalry","amount":1},{"name":"Archfiend Cavalry","amount":1},{"name":"Archfiend Cavalry","amount":1},{"name":"Archfiend's Roar","amount":1},{"name":"Archfiend's Roar","amount":1},{"name":"Archfiend's Roar","amount":1},{"name":"Escape from the Dark Dimension","amount":1},{"name":"Escape from the Dark Dimension","amount":1},{"name":"Needlebug Nest","amount":1},{"name":"Needlebug Nest","amount":1},{"name":"Needlebug Nest","amount":1},{"name":"Call of the Archfiend","amount":1},{"name":"Call of the Archfiend","amount":1},{"name":"Call of the Archfiend","amount":1}],"extra":[],"notes":[{"text":"Shout out to the golden fish dude who econ stole my emperor after i spec summoned him in def mode. Congratulations. You played yourself."}],"url":"/top-decks/april-2018/archfiends/emperor-of-bacon-by-bacon-fiend-expert/"}
