{"_id":"98f2b9d0-4b6e-11e8-9d89-87f59e4b29ef","name":"##","deckType":"archfiends","skill":"Restart","author":"Lightning","notes":"","main0":"Archfiend Emperor, the First Lord of Horror","main1":"Archfiend Emperor, the First Lord of Horror","main2":"Archfiend Emperor, the First Lord of Horror","main3":"Archfiend Empress","main4":"Archfiend Empress","main5":"Archfiend Empress","main6":"Archfiend Cavalry","main7":"Archfiend Cavalry","main8":"Jain, Lightsworn Paladin","main9":"Snipe Hunter","main10":"Monster Gate","main11":"Archfiend's Roar","main12":"Archfiend's Roar","main13":"Archfiend's Roar","main14":"Needlebug Nest","main15":"Needlebug Nest","main16":"Needlebug Nest","main17":"Call of the Archfiend","main18":"Call of the Archfiend","main19":"Call of the Archfiend","date":"2018-04-29T05:31:42.609Z","pageless":true,"templateKey":"comments","tags":[]}