{"_id":"2ff5faa0-0ded-11e8-8094-4f25368a15b0","name":"I seriously can't win with anything rn","deckType":"dark-magician","skill":"Master of Magicians","author":"stealth sub","notes":">spend 6 days grinding with dinos, magnets, etc\r\n>get frustrated\r\n>forget it, we dark magician for memes now\r\n>don't lose\r\n>brick once\r\n>besides that\r\n>never lose\r\n>meme my way into KOG\r\n>dark magic attack\r\n\r\npeople shouldn't have dropped sergeant electro, electro + floodgate + mirror wall is still secure af for locking down the field and waiting to draw a combo","main0":"Magician's Rod","main1":"Magician's Rod","main2":"Sergeant Electro","main3":"Sergeant Electro","main4":"Sergeant Electro","main5":"Legion the Fiend Jester","main6":"Legion the Fiend Jester","main7":"Dark Magician","main8":"Dark Magician","main9":"Dark Magician","main10":"Ancient Rules","main11":"Ancient Rules","main12":"Dark Magic Attack","main13":"Dark Magic Curtain","main14":"Thousand Knives","main15":"Champion's Vigilance","main16":"Floodgate Trap Hole","main17":"Floodgate Trap Hole","main18":"Mirror Wall","main19":"Mirror Wall","date":"2018-02-09T23:01:40.196Z","layout":"post","message":" ","timestamp":1518217300,"tags":["user-generated"]}