{"_id":"857bca70-0228-11e8-9a84-7fd1a392669e","name":"REZ3","deckType":"red-eyes-zombies","skill":"Straight to the Grave","author":"danyeo","notes":"REZ deck for the stats, I had a hard time vs Arkana / dark magician. There isn't anything to really storm unless they are careless with their spells and their DM beats REZ. Econ take the DM when he first gets summoned if possible to distrupt their backrow clearing spell.","main0":"Red-Eyes Zombie Dragon","main1":"Red-Eyes Zombie Dragon","main2":"Gozuki","main3":"Gozuki","main4":"Gozuki","main5":"Samurai Skull","main6":"Samurai Skull","main7":"Bacon Saver","main8":"Enemy Controller","main9":"Enemy Controller","main10":"Red-Eyes Insight","main11":"Red-Eyes Insight","main12":"Storm","main13":"Storm","main14":"Super Rush Headlong","main15":"Super Rush Headlong","main16":"Curse of Anubis","main17":"Red-Eyes Spirit","main18":"Red-Eyes Spirit","main19":"Windstorm of Etaqua","date":"2018-01-25T23:36:09.970Z"}