{"_id":"7f0466a0-2354-11e8-b4f9-27c2acd22910","name":"##","deckType":"destiny-heroes","skill":"Destiny Calling","author":"AkatsuRed","notes":"Basically Dkayed's build but with e-cons and I don't have level 40 master so no malicious","main0":"Destiny HERO - Celestial","main1":"Destiny HERO - Celestial","main2":"Destiny HERO - Celestial","main3":"Destiny HERO - Decider","main4":"Destiny HERO - Decider","main5":"Destiny HERO - Decider","main6":"The Dark - Hex-Sealed Fusion","main7":"The Dark - Hex-Sealed Fusion","main8":"Vision HERO Vyon","main9":"Vision HERO Vyon","main10":"Vision HERO Vyon","main11":"Destiny HERO - Dreamer","main12":"Enemy Controller","main13":"Enemy Controller","main14":"Enemy Controller","main15":"Polymerization","main16":"Polymerization","main17":"Polymerization","main18":"Powerful Rebirth","main19":"Powerful Rebirth","extra0":"Red-Eyes Slash Dragon","extra1":"Red-Eyes Slash Dragon","extra2":"Vision HERO Trinity","extra3":"Destiny HERO - Dangerous","extra4":"Destiny HERO - Dangerous","date":"2018-03-09T04:44:05.414Z"}