{"_id":"754b3110-f088-11e7-83bb-b50b8e36fc3b","name":"I equip a spell card","deckType":"burn-decks","skill":"Duel, standby!","author":"Hufflepuff","notes":"","main0":"Woodland Sprite","main1":"Woodland Sprite","main2":"Woodland Sprite","main3":"Black Pendant","main4":"Black Pendant","main5":"Black Pendant","main6":"Broken Bamboo Sword","main7":"Broken Bamboo Sword","main8":"Broken Bamboo Sword","main9":"Cup of Ace","main10":"Cup of Ace","main11":"Cursed Bamboo Sword","main12":"Cursed Bamboo Sword","main13":"Cursed Bamboo Sword","main14":"Golden Bamboo Sword","main15":"Golden Bamboo Sword","main16":"Golden Bamboo Sword","main17":"Into the Void","main18":"Into the Void","main19":"Magical Mallet","date":"2018-01-03T13:17:33.527Z"}