{"_id":"0ff25fd0-2ba9-11e8-9df1-79a13d8c7066","name":"E.T Come Home","deckType":"sylvans","skill":"Restart","author":"CrimsonKillua","notes":"My kog deck was pretty easy honestly just set the merchant and hope for the best then trundae for game I don’t have a lot of mushrooms so if I had more I’d use em but honestly didn’t miss them just straight up destroyed people","main0":"Sylvan Hermitree","main1":"Sylvan Hermitree","main2":"Sylvan Hermitree","main3":"Sylvan Guardioak","main4":"Sylvan Guardioak","main5":"Sylvan Guardioak","main6":"World Carrotweight Champion","main7":"World Carrotweight Champion","main8":"Sylvan Marshalleaf","main9":"Sylvan Marshalleaf","main10":"Sylvan Marshalleaf","main11":"Rose Lover","main12":"Rose Lover","main13":"Rose Lover","main14":"Magical Merchant","main15":"Magical Merchant","main16":"Magical Merchant","main17":"Outstanding Dog Marron","main18":"Sylvan Komushroomo","main19":"Hey, Trunade!","date":"2018-03-19T19:09:35.636Z","layout":"post","message":" "}