{"_id":"93f3d6a0-297a-11e8-9355-9ff5c65d6e8d","name":"A Song of Wind","deckType":"cyber-angels","skill":"Duel, standby!","author":"Milliardo","notes":"From L1 to KoG I only lost 2 games, one of them was stalk and the other was a complete brick. I honestly still don’t think this is the perfect card-ratio, but I am getting close.","main0":"Cyber Angel Dakini","main1":"Cyber Angel Dakini","main2":"Saffira, Queen of Dragons","main3":"Saffira, Queen of Dragons","main4":"Cyber Angel Benten","main5":"Cyber Angel Benten","main6":"Cyber Angel Idaten","main7":"Senju of the Thousand Hands","main8":"Senju of the Thousand Hands","main9":"Cyber Petit Angel","main10":"Cyber Petit Angel","main11":"Hymn of Light","main12":"Hymn of Light","main13":"Machine Angel Absolute Ritual","main14":"Machine Angel Absolute Ritual","main15":"Sprite's Blessing","main16":"Sprite's Blessing","main17":"Sprite's Blessing","main18":"Hey, Trunade!","main19":"Hey, Trunade!","date":"2018-03-17T00:31:48.350Z","layout":"post"}