{"_id":"f2389af0-21c5-11e8-a2b2-bb1a543b87b2","name":"Fish & chips","deckType":"sea-stealth-attack","skill":"Mythic Depths","author":"Loo","notes":"Copy paste top 4 mcs\r\nThe reorder from gishki is nice! \r\nAlso when gishki is flipped draw gishki to res gishki and summon big wealth to get ssa","main0":"Citadel Whale","main1":"Citadel Whale","main2":"Citadel Whale","main3":"Warrior of Atlantis","main4":"Warrior of Atlantis","main5":"Abyss Soldier","main6":"Abyss Soldier","main7":"Abyss Soldier","main8":"Gishki Chain","main9":"Gishki Chain","main10":"Gishki Beast","main11":"Gishki Ariel","main12":"Gishki Ariel","main13":"Gishki Ariel","main14":"A Legendary Ocean","main15":"Cosmic Cyclone","main16":"Cosmic Cyclone","main17":"Sea Stealth Attack","main18":"Sea Stealth Attack","main19":"Sea Stealth Attack","main20":"Wall of Disruption","main21":"Wall of Disruption","date":"2018-03-07T05:11:09.411Z","tags":["comment-subscription"]}