{"_id":"990e7770-1cc4-11e8-abc6-93a9950ae90a","name":"CAFFIRA","deckType":"cyber-angels","skill":"Balance","author":"UtimixZero","notes":"","main0":"Vennu, Bright Bird of Divinity","main1":"Cyber Angel Dakini","main2":"Saffira, Queen of Dragons","main3":"Saffira, Queen of Dragons","main4":"Cyber Angel Benten","main5":"Cyber Angel Benten","main6":"Cyber Angel Benten","main7":"Cyber Angel Idaten","main8":"Senju of the Thousand Hands","main9":"Senju of the Thousand Hands","main10":"Senju of the Thousand Hands","main11":"Bacon Saver","main12":"Cyber Petit Angel","main13":"Hymn of Light","main14":"Hymn of Light","main15":"Hymn of Light","main16":"Machine Angel Absolute Ritual","main17":"Machine Angel Ritual","main18":"Sprite's Blessing","main19":"Sprite's Blessing","date":"2018-02-28T20:18:54.570Z","layout":"post"}