{"_id":"d0902cf0-f165-11e7-9668-8d5639c5ebab","name":"Cyber Angels","deckType":"cyber-angels","skill":"Restart","author":"decj99","notes":"Got up to Legend 3 with Magnets on a long win streak, then after bouncing around in legend, I finished it off with Cybers","main0":"Cyber Angel Dakini","main1":"Cyber Angel Dakini","main2":"Cyber Angel Dakini","main3":"Cyber Angel Benten","main4":"Cyber Angel Benten","main5":"Cyber Angel Benten","main6":"Cyber Angel Idaten","main7":"Senju of the Thousand Hands","main8":"Senju of the Thousand Hands","main9":"Sonic Bird","main10":"Cyber Petit Angel","main11":"Cyber Petit Angel","main12":"Enemy Controller","main13":"Enemy Controller","main14":"Enemy Controller","main15":"Machine Angel Absolute Ritual","main16":"Machine Angel Absolute Ritual","main17":"Machine Angel Absolute Ritual","main18":"Machine Angel Ritual","main19":"Sprite's Blessing","date":"2018-01-04T15:42:05.542Z"}