{"_id":"f7079e30-5f89-11e8-a61a-4128d6332cf8","name":"Cyber Angels","deckType":"cyber-angels","skill":"Grit","author":"sun","notes":"Kog in 57 wins after trying out a lot of different things. Ran into a lot less econs than the last time I got kog with CAs which made me want to try out Balance but stayed with Grit. It made me brick a couple times but it also saved my streak as well.","main0":"Cyber Angel Dakini","main1":"Saffira, Queen of Dragons","main2":"Saffira, Queen of Dragons","main3":"Cyber Angel Benten","main4":"Cyber Angel Benten","main5":"Cyber Angel Benten","main6":"Gishki Chain","main7":"Cyber Angel Idaten","main8":"Senju of the Thousand Hands","main9":"Senju of the Thousand Hands","main10":"Senju of the Thousand Hands","main11":"Cyber Petit Angel","main12":"Cyber Petit Angel","main13":"Hymn of Light","main14":"Hymn of Light","main15":"Machine Angel Absolute Ritual","main16":"Machine Angel Ritual","main17":"Sprite's Blessing","main18":"Sprite's Blessing","main19":"Sprite's Blessing","timestamp":1527190679,"date":"2018-05-24T19:37:59.783Z","tags":["comment-subscription"]}