{"_id":"ac23f7c0-4e62-11e8-8aab-efdbeaad8bc2","name":"Destiny Hero","deckType":"masked-heroes","skill":"Restart","author":"Snyffus","notes":"Played a pretty standard Masked D-Hero list to get KoG because it is the best deck right now but the new box and Amazoness are gonna shake up the meta so we have to see what happens, maybe one of these decks is better.\r\nChanged some cards during the run, like Trunade and Treacherous and TTTD and Im still not sure what the deck should look like after the release of Spellbooks and tomorrow Amazoness, more testing needs to be done and MCS VIII next week will show what the top decks and the meta are going to be.","main0":"Destiny HERO - Celestial","main1":"Destiny HERO - Celestial","main2":"Destiny HERO - Celestial","main3":"Destiny HERO - Decider","main4":"Vision HERO Vyon","main5":"Vision HERO Vyon","main6":"Vision HERO Vyon","main7":"Destiny HERO - Malicious","main8":"Destiny HERO - Malicious","main9":"Destiny HERO - Dreamer","main10":"Destiny Draw","main11":"Enemy Controller","main12":"Enemy Controller","main13":"Forbidden Chalice","main14":"Forbidden Chalice","main15":"Hey, Trunade!","main16":"Mask Change","main17":"Mask Change","main18":"Mask Change","main19":"Polymerization","main20":"Treacherous Trap Hole","extra0":"Masked HERO Anki","extra1":"Masked HERO Anki","extra2":"Masked HERO Anki","extra3":"Vision HERO Trinity","extra4":"Destiny HERO - Dangerous","date":"2018-05-02T23:43:53.997Z","tags":[]}