{"_id":"6e9356a0-1f4e-11e8-8e5c-bbd9119aac8b","name":"(KOG) Oyster Moister","deckType":"hammer-shark","skill":"Mythic Depths","author":"Heracles","notes":"This was by far the most fun KoG climb in my DL career\r\nMost matchups were against other water and aliiiens","main0":"Golden Flying Fish","main1":"Golden Flying Fish","main2":"Golden Flying Fish","main3":"Hammer Shark","main4":"Hammer Shark","main5":"Hammer Shark","main6":"Oyster Meister","main7":"Oyster Meister","main8":"Oyster Meister","main9":"Beautunaful Princess","main10":"Enemy Controller","main11":"Enemy Controller","main12":"Enemy Controller","main13":"Storm","main14":"Fish Depth Charge","main15":"Powerful Rebirth","main16":"Powerful Rebirth","main17":"Powerful Rebirth","main18":"Wall of Disruption","main19":"Wall of Disruption","date":"2018-03-04T01:50:36.151Z"}