{"_id":"82393520-e214-11e7-a76b-dd4e37b68aa6","name":"PvP","author":"mpveras","deckType":"dinos","skill":"Dinosaur Kingdom","notes":"Dinos? More like anti-CA back row","main0":"Black Brachios","main1":"Black Brachios","main2":"Hydrogeddon","main3":"Hydrogeddon","main4":"Hydrogeddon","main5":"Sergeant Electro","main6":"Sergeant Electro","main7":"Sergeant Electro","main8":"Enemy Controller","main9":"Enemy Controller","main10":"Enemy Controller","main11":"Forbidden Chalice","main12":"Forbidden Chalice","main13":"Fossil Dig","main14":"Floodgate Trap Hole","main15":"Floodgate Trap Hole","main16":"Floodgate Trap Hole","main17":"Mirror Wall","main18":"Mirror Wall","main19":"Mirror Wall","date":"2017-12-16T03:52:17.418Z","timestamp":1513396337}