{"_id":"c3fe4d80-3c30-11e8-8416-c58ae797a8c2","name":"##","deckType":"cyber-angels","skill":"Balance","author":"iHateDisGame","notes":"got kog with this on april 1st, not sure if its viable anymore","main0":"Cyber Angel Dakini","main1":"Saffira, Queen of Dragons","main2":"Saffira, Queen of Dragons","main3":"Saffira, Queen of Dragons","main4":"Cyber Angel Benten","main5":"Cyber Angel Benten","main6":"Cyber Angel Benten","main7":"Gishki Chain","main8":"Cyber Angel Idaten","main9":"Senju of the Thousand Hands","main10":"Senju of the Thousand Hands","main11":"Senju of the Thousand Hands","main12":"Cyber Petit Angel","main13":"Hymn of Light","main14":"Hymn of Light","main15":"Hymn of Light","main16":"Machine Angel Absolute Ritual","main17":"Machine Angel Ritual","main18":"Sprite's Blessing","main19":"Sprite's Blessing","date":"2018-04-09T20:01:18.263Z"}