{"_id":"a041d0a0-234a-11e8-b4f9-27c2acd22910","name":"##","deckType":"archfiends","skill":"LP Boost α","author":"davidoff","notes":"Is destroyed allot of meta decks with this and with the empress lord of horror combo i destroyed ssa this deck is a tier deck for Sure 3-2","main0":"Archfiend Emperor, the First Lord of Horror","main1":"Archfiend Emperor, the First Lord of Horror","main2":"Archfiend Emperor, the First Lord of Horror","main3":"Archfiend Empress","main4":"Trance Archfiend","main5":"Trance Archfiend","main6":"Trance Archfiend","main7":"Doomdog Octhros","main8":"Doomdog Octhros","main9":"Doomdog Octhros","main10":"Advance Draw","main11":"Advance Draw","main12":"Card of the Soul","main13":"Card of the Soul","main14":"Card of the Soul","main15":"Escape from the Dark Dimension","main16":"Escape from the Dark Dimension","main17":"Call of the Archfiend","main18":"Call of the Archfiend","main19":"Call of the Archfiend","date":"2018-03-09T03:33:26.217Z"}