{"_id":"4d636470-003b-11e8-ab0e-6f6c72cf2eed","name":"Dark Knight","deckType":"dark-world","skill":"Duel, standby!","author":"Gatecityg","notes":"","main0":"Reign-Beaux, Overlord of Dark World","main1":"Reign-Beaux, Overlord of Dark World","main2":"Dark Necrofear","main3":"Snoww, Unlight of Dark World","main4":"Snoww, Unlight of Dark World","main5":"Trance Archfiend","main6":"Trance Archfiend","main7":"Trance Archfiend","main8":"Broww, Huntsman of Dark World","main9":"Sphere Kuriboh","main10":"Sphere Kuriboh","main11":"Ceruli, Guru of Dark World","main12":"Ceruli, Guru of Dark World","main13":"Dark World Dealings","main14":"Dark World Dealings","main15":"Dark World Lightning","main16":"Dark World Lightning","main17":"Dark Smog","main18":"Floodgate Trap Hole","main19":"Floodgate Trap Hole","date":"2018-01-23T12:45:34.054Z"}