{"_id":"5b333ea0-0eb3-11e8-b9d0-9dcdc2f1c11f","name":"##Cyber Angels","deckType":"cyber-angels","skill":"Balance","author":"Pelat","notes":"It's the same of 95% of other KoG decks xD","main0":"Cyber Angel Dakini","main1":"Saffira, Queen of Dragons","main2":"Saffira, Queen of Dragons","main3":"Cyber Angel Benten","main4":"Cyber Angel Benten","main5":"Cyber Angel Benten","main6":"Cyber Angel Idaten","main7":"Senju of the Thousand Hands","main8":"Senju of the Thousand Hands","main9":"Senju of the Thousand Hands","main10":"Cyber Petit Angel","main11":"Fenghuang","main12":"Hymn of Light","main13":"Hymn of Light","main14":"Hymn of Light","main15":"Machine Angel Absolute Ritual","main16":"Machine Angel Ritual","main17":"Sprite's Blessing","main18":"Sprite's Blessing","main19":"Sprite's Blessing","date":"2018-02-10T22:40:13.011Z","tags":["user-generated"],"timestamp":1518302413}