{"_id":"0349cb00-0df0-11e8-8094-4f25368a15b0","name":"Red Eyes Zombie","deckType":"red-eyes-zombies","skill":"Straight to the Grave","author":"Mat Ox","notes":"Another REZ for the stats","main0":"Red-Eyes Zombie Dragon","main1":"Red-Eyes Zombie Dragon","main2":"Red-Eyes Wyvern","main3":"Gozuki","main4":"Gozuki","main5":"Samurai Skull","main6":"Samurai Skull","main7":"Samurai Skull","main8":"Bacon Saver","main9":"Enemy Controller","main10":"Enemy Controller","main11":"Enemy Controller","main12":"Red-Eyes Insight","main13":"Red-Eyes Insight","main14":"Storm","main15":"Storm","main16":"Storm","main17":"Red-Eyes Spirit","main18":"Red-Eyes Spirit","main19":"Wall of Disruption","main20":"Wall of Disruption","date":"2018-02-09T23:21:53.730Z","layout":"post","message":" ","timestamp":1518218513,"tags":["user-generated"]}