{"_id":"15198870-5f99-11e8-a61a-4128d6332cf8","name":"sylvan base 3","deckType":"sylvans","skill":"Grit","author":"emmentch","notes":"Standard Sylvans, first KoG for me. Did well on the ladder.","main0":"Sylvan Hermitree","main1":"Sylvan Hermitree","main2":"Sylvan Guardioak","main3":"Sylvan Guardioak","main4":"Sylvan Guardioak","main5":"World Carrotweight Champion","main6":"World Carrotweight Champion","main7":"Sylvan Marshalleaf","main8":"Sylvan Marshalleaf","main9":"Sylvan Marshalleaf","main10":"Rose Lover","main11":"Rose Lover","main12":"Rose Lover","main13":"Sylvan Komushroomo","main14":"Sylvan Komushroomo","main15":"Sylvan Komushroomo","main16":"Enemy Controller","main17":"Enemy Controller","main18":"Tribute to the Doomed","main19":"Treacherous Trap Hole","timestamp":1527197172,"date":"2018-05-24T21:26:12.684Z","tags":["comment-subscription"]}