{"_id":"4e09ee30-297b-11e8-9355-9ff5c65d6e8d","name":"Hazy Farm","deckType":"hazy-flame","skill":"Aroma Strategy","author":"Machdragon","notes":"+1 Hazy Stats","main0":"Hazy Flame Cerbereus","main1":"Hazy Flame Cerbereus","main2":"Hazy Flame Cerbereus","main3":"Hazy Flame Sphynx","main4":"Hazy Flame Sphynx","main5":"Hazy Flame Sphynx","main6":"Dynatherium","main7":"Caninetaur","main8":"Caninetaur","main9":"Magic Planter","main10":"Soul Exchange","main11":"Soul Exchange","main12":"Soul Exchange","main13":"Beast Rising","main14":"Beast Rising","main15":"Beast Rising","main16":"Hazy Glory","main17":"Mirror Wall","main18":"Mirror Wall","main19":"Xing Zhen Hu","date":"2018-03-17T00:37:00.509Z","layout":"post"}