{"_id":"5fcf13e0-e27f-11e7-9ed7-6b1230e73f07","name":"Hazy Flames","author":"Fox","deckType":"hazy-flame-br","skill":"Aroma Strategy","notes":"If you subtract a bunch of quick misclicks and testing, I really only needed about 30 games","main0":"Hazy Flame Cerbereus","main1":"Hazy Flame Cerbereus","main2":"Hazy Flame Sphynx","main3":"Hazy Flame Sphynx","main4":"Hazy Flame Sphynx","main5":"Flame Tiger","main6":"Sergeant Electro","main7":"Caninetaur","main8":"Caninetaur","main9":"Enemy Controller","main10":"Enemy Controller","main11":"Enemy Controller","main12":"Soul Exchange","main13":"Soul Exchange","main14":"Soul Exchange","main15":"Beast Rising","main16":"Beast Rising","main17":"Floodgate Trap Hole","main18":"Floodgate Trap Hole","main19":"Floodgate Trap Hole","date":"2017-12-16T16:37:15.748Z"}