{"_id":"fc42a4b0-173d-11e8-b61b-7b344215416b","name":"Empty Wallet Control :(","deckType":"control-decks","skill":"Switcheroo","author":"Secret_Lizard_Person","notes":"Ultimate providence won me 2/5 legend 3 games against gladiator beasts. I got my second snipe hunter with the gems I got from KOG.","main0":"Volcanic Rocket","main1":"Volcanic Rocket","main2":"Volcanic Rocket","main3":"Sergeant Electro","main4":"Sergeant Electro","main5":"Sergeant Electro","main6":"Snipe Hunter","main7":"Sphere Kuriboh","main8":"Volcanic Shell","main9":"Volcanic Shell","main10":"Volcanic Shell","main11":"Blaze Accelerator","main12":"Enemy Controller","main13":"Enemy Controller","main14":"Enemy Controller","main15":"Floodgate Trap Hole","main16":"Floodgate Trap Hole","main17":"Ultimate Providence","main18":"Wall of Disruption","main19":"Wall of Disruption","date":"2018-02-21T19:32:43.105Z","approved":false,"title":"Comment"}