{"_id":"dbd22bb0-5f95-11e8-a61a-4128d6332cf8","name":"Click YES for Bakura","deckType":"sylvans","skill":"Grit","author":"MaliceStriker","notes":"Third KoG in a row with Sylvans. I used a different skill each time, this time being Grit. Got to KoG in 39 wins. Standard build for the most part. 2 Econ and TTH are all you need really. 4th backrow can literally be anything - it doesn't matter.","main0":"Sylvan Hermitree","main1":"Sylvan Hermitree","main2":"Sylvan Guardioak","main3":"Sylvan Guardioak","main4":"Sylvan Lotuswain","main5":"World Carrotweight Champion","main6":"World Carrotweight Champion","main7":"Sylvan Marshalleaf","main8":"Sylvan Marshalleaf","main9":"Sylvan Marshalleaf","main10":"Rose Lover","main11":"Rose Lover","main12":"Rose Lover","main13":"Sylvan Komushroomo","main14":"Sylvan Komushroomo","main15":"Sylvan Komushroomo","main16":"Anti-Magic Arrows","main17":"Enemy Controller","main18":"Enemy Controller","main19":"Treacherous Trap Hole","timestamp":1527195788,"date":"2018-05-24T21:03:08.093Z","tags":["comment-subscription"]}