{"_id":"60ea53c0-42ba-11e8-bd95-5d24bbe55069","name":"Sylvan Meta","deckType":"sylvans","skill":"Restart","author":"Game_Planner","notes":"","main0":"Sylvan Hermitree","main1":"Sylvan Hermitree","main2":"Sylvan Guardioak","main3":"Sylvan Guardioak","main4":"World Carrotweight Champion","main5":"World Carrotweight Champion","main6":"Sylvan Marshalleaf","main7":"Sylvan Marshalleaf","main8":"Sylvan Marshalleaf","main9":"Rose Lover","main10":"Rose Lover","main11":"Rose Lover","main12":"Sylvan Komushroomo","main13":"Sylvan Komushroomo","main14":"Sylvan Komushroomo","main15":"Enemy Controller","main16":"Enemy Controller","main17":"Ultimate Providence","main18":"Ultimate Providence","main19":"Ultimate Providence","date":"2018-04-18T03:41:29.548Z","timestamp":1524022889}