{"_id":"c50b3f90-2aeb-11e8-86f2-611b1a84ae15","name":"Standby CA","deckType":"cyber-angels","skill":"Duel, standby!","author":"EnriqueCG","notes":"","main0":"Cyber Angel Dakini","main1":"Saffira, Queen of Dragons","main2":"Saffira, Queen of Dragons","main3":"Cyber Angel Benten","main4":"Cyber Angel Benten","main5":"Cyber Angel Benten","main6":"Cyber Angel Idaten","main7":"Senju of the Thousand Hands","main8":"Senju of the Thousand Hands","main9":"Cyber Petit Angel","main10":"Cyber Petit Angel","main11":"Hymn of Light","main12":"Hymn of Light","main13":"Machine Angel Absolute Ritual","main14":"Machine Angel Absolute Ritual","main15":"Machine Angel Ritual","main16":"Sprite's Blessing","main17":"Sprite's Blessing","main18":"Hey, Trunade!","main19":"Hey, Trunade!","extra0":"Five-Headed Dragon","extra1":"Five-Headed Dragon","extra2":"Five-Headed Dragon","extra3":"Blue-Eyes Ultimate Dragon","extra4":"Blue-Eyes Ultimate Dragon","date":"2018-03-18T20:34:34.951Z"}