{"_id":"fabecf60-4f5a-11e8-91ca-0b01cd25e880","name":"Good ol' veggies","deckType":"sylvans","skill":"Grit","author":"CkM","notes":"","main0":"Sylvan Hermitree","main1":"Sylvan Hermitree","main2":"Sylvan Guardioak","main3":"Sylvan Guardioak","main4":"Sylvan Guardioak","main5":"World Carrotweight Champion","main6":"World Carrotweight Champion","main7":"Sylvan Marshalleaf","main8":"Sylvan Marshalleaf","main9":"Sylvan Marshalleaf","main10":"Rose Lover","main11":"Rose Lover","main12":"Rose Lover","main13":"Sylvan Komushroomo","main14":"Sylvan Komushroomo","main15":"Sylvan Komushroomo","main16":"Enemy Controller","main17":"Enemy Controller","main18":"Enemy Controller","main19":"Treacherous Trap Hole","date":"2018-05-04T05:21:21.051Z","tags":[],"pageless":true,"templateKey":"comments","timestamp":1525411281,"layout":"post","message":" "}