{"_id":"56639f40-e2ef-11e7-9323-5d20ea4b866a","name":"Hazy Gun","author":"christefanu","deckType":"hazy-flame-br","skill":"Three-Star Demotion","notes":"After Ninjas brang me to legend3 and tilted me back to legend1 with only monster brick hands vs ca I decided to give 3SD Hazy a try and Iiterally destroyed my opponents and got fast wins. Score was like 18-3 definitely credit to BuiltToTilt. Many opponents tried to attack Hazy when theres no backrow like br so i teched WOD (for ca and mirror) since AG were rare for me","main0":"Great Shogun Shien","main1":"Hazy Flame Cerbereus","main2":"Hazy Flame Cerbereus","main3":"Hazy Flame Cerbereus","main4":"Hazy Flame Sphynx","main5":"Hazy Flame Sphynx","main6":"Hazy Flame Sphynx","main7":"Flame Tiger","main8":"Flame Tiger","main9":"Flame Tiger","main10":"Hazy Flame Peryton","main11":"Hazy Flame Peryton","main12":"Hazy Flame Peryton","main13":"Sphere Kuriboh","main14":"Sphere Kuriboh","main15":"Enemy Controller","main16":"Enemy Controller","main17":"Beast Rising","main18":"Beast Rising","main19":"Wall of Disruption","date":"2017-12-17T05:58:43.579Z"}