{"_id":"9faa6050-2cc6-11e8-9f0c-3b52df5f76db","name":"##","deckType":"sylvans","skill":"Restart","author":"B1a Z3n","notes":"Deck is broken went from plat 3 to KOG with only a few loses due to severe misplays. Had been out of the game for a bit so was happy to find something fun to play, Ultimate Providence won so many games due to hitting both monsters and traps, 100% better than d-wrath IMHO","main0":"Mariña, Princess of Sunflowers","main1":"Mariña, Princess of Sunflowers","main2":"Sylvan Hermitree","main3":"Sylvan Hermitree","main4":"World Carrotweight Champion","main5":"World Carrotweight Champion","main6":"Sylvan Marshalleaf","main7":"Sylvan Marshalleaf","main8":"Sylvan Marshalleaf","main9":"Rose Lover","main10":"Rose Lover","main11":"Rose Lover","main12":"Sylvan Komushroomo","main13":"Sylvan Komushroomo","main14":"Sylvan Komushroomo","main15":"Jar of Avarice","main16":"Jar of Avarice","main17":"Ultimate Providence","main18":"Ultimate Providence","main19":"Ultimate Providence","date":"2018-03-21T05:13:43.204Z"}