{"name":"100% Original and Innovative Deck","top-player-council":false,"author":"Yami Hammy","created":"2018-03-29","skill":"Balance","main":[{"name":"Saffira, Queen of Dragons","amount":1},{"name":"Saffira, Queen of Dragons","amount":1},{"name":"Cyber Angel Dakini","amount":1},{"name":"Cyber Angel Benten","amount":1},{"name":"Cyber Angel Benten","amount":1},{"name":"Cyber Angel Benten","amount":1},{"name":"Cyber Angel Idaten","amount":1},{"name":"Senju of the Thousand Hands","amount":1},{"name":"Senju of the Thousand Hands","amount":1},{"name":"Senju of the Thousand Hands","amount":1},{"name":"Cyber Petit Angel","amount":1},{"name":"Cyber Petit Angel","amount":1},{"name":"Cosmic Cyclone","amount":1},{"name":"Hymn of Light","amount":1},{"name":"Hymn of Light","amount":1},{"name":"Machine Angel Absolute Ritual","amount":1},{"name":"Machine Angel Ritual","amount":1},{"name":"Sprite's Blessing","amount":1},{"name":"Sprite's Blessing","amount":1},{"name":"Hey, Trunade!","amount":1}],"extra":[],"notes":[{"text":"I was busy with website stuff so I got KoG really late this month, but KoG is KoG ¯\\_(ツ)_/¯"}],"url":"/top-decks/march-2018/cyber-angels/100-original-and-innovative-deck-by-yami-hammy/"}
