{"name":"Ancient Gears","author":"mhopson69","created":"2018-02-09","skill":"Middle Age Mechs","main":[{"name":"Ancient Gear Golem","amount":1},{"name":"Ancient Gear Golem","amount":1},{"name":"Ancient Gear Beast","amount":1},{"name":"Ancient Gear Knight","amount":1},{"name":"Ancient Gear Knight","amount":1},{"name":"Ancient Gear Knight","amount":1},{"name":"Sergeant Electro","amount":1},{"name":"Sergeant Electro","amount":1},{"name":"Sergeant Electro","amount":1},{"name":"Sphere Kuriboh","amount":1},{"name":"Sphere Kuriboh","amount":1},{"name":"Enemy Controller","amount":1},{"name":"Enemy Controller","amount":1},{"name":"Super Rush Headlong","amount":1},{"name":"Curse of Anubis","amount":1},{"name":"Floodgate Trap Hole","amount":1},{"name":"Floodgate Trap Hole","amount":1},{"name":"Wall of Disruption","amount":1},{"name":"Wall of Disruption","amount":1},{"name":"Windstorm of Etaqua","amount":1}],"extra":[],"notes":[{"text":"Countered Glad beasts, burn, and mill very well. Did pretty good against cyber angels as well"}],"url":"/top-decks/february-2018/ancient-gears/ancient-gears-by-mhopson69/"}
